fastgaia/__init__.py
fastgaia/cli.py
fastgaia/main.py
fastgaia-0.1.2.dist-info/licenses/LICENSE
fastgaia-0.1.2.dist-info/METADATA
fastgaia-0.1.2.dist-info/WHEEL
fastgaia-0.1.2.dist-info/entry_points.txt
fastgaia-0.1.2.dist-info/top_level.txt
fastgaia-0.1.2.dist-info/RECORD
