Metadata-Version: 2.4
Name: fastgaia
Version: 0.1.2
Summary: A tool to infer node locations and states from tree sequences.
Home-page: https://github.com/chris-a-talbot/fastgaia
Author: Chris Talbot
Author-email: cat267@cornell.edu
License: MIT
Classifier: Programming Language :: Python :: 3
Classifier: License :: OSI Approved :: MIT License
Classifier: Operating System :: OS Independent
Requires-Python: >=3.7
License-File: LICENSE
Requires-Dist: numpy
Requires-Dist: pandas
Requires-Dist: tskit
Dynamic: license-file
